MANIFEST.in
README.md
setup.py
django_mp_manufacturers.egg-info/PKG-INFO
django_mp_manufacturers.egg-info/SOURCES.txt
django_mp_manufacturers.egg-info/dependency_links.txt
django_mp_manufacturers.egg-info/top_level.txt
manufacturers/__init__.py
manufacturers/admin.py
manufacturers/models.py
manufacturers/settings.py
manufacturers/signals.py
manufacturers/tasks.py
manufacturers/tests.py
manufacturers/urls.py
manufacturers/utils.py
manufacturers/views.py
manufacturers/locale/ru/LC_MESSAGES/django.mo
manufacturers/locale/ru/LC_MESSAGES/django.po
manufacturers/locale/uk/LC_MESSAGES/django.mo
manufacturers/locale/uk/LC_MESSAGES/django.po
manufacturers/migrations/0001_initial.py
manufacturers/migrations/0002_manufacturer_new_name.py
manufacturers/migrations/0003_manufacturer_supplier_id.py
manufacturers/migrations/__init__.py