Metadata-Version: 2.1
Name: django-mp-manufacturers
Version: 1.0.2
Summary: Django manufacturers app
Home-page: https://github.com/pmaigutyak/mp-manufacturers
Author: Paul Maigutyak
Author-email: pmaigutyak@gmail.com
License: MIT
Download-URL: https://github.com/pmaigutyak/mp-manufacturers/archive/1.0.2.tar.gz
Platform: UNKNOWN
